MANIFEST.in
NEWS.txt
README.rst
setup.py
stupeflix_api/__init__.py
stupeflix_api/commandline.py
stupeflix_api/conf.py
stupeflix_api/connection.py
stupeflix_api/demjson.py
stupeflix_api/key.py
stupeflix_api/stupeflix.py
stupeflix_api/stupeflixbase.py
stupeflix_api/taskclient.py
stupeflix_api.egg-info/PKG-INFO
stupeflix_api.egg-info/SOURCES.txt
stupeflix_api.egg-info/dependency_links.txt
stupeflix_api.egg-info/entry_points.txt
stupeflix_api.egg-info/not-zip-safe
stupeflix_api.egg-info/top_level.txt
stupeflix_api/httplib2/__init__.py
stupeflix_api/httplib2/encode.py
stupeflix_api/httplib2/iri2uri.py
stupeflix_api/tests/__init__.py
stupeflix_api/tests/test_connection.py