Metadata-Version: 1.0
Name: stupeflix-api
Version: 0.3.0
Summary: Stupeflix web services client libraries
Home-page: https://github.com/stupeflix/Stupeflix-API-Client
Author: Francois Lagunas
Author-email: francois@stupeflix.com
License: UNKNOWN
Platform: UNKNOWN
